archielle_tools/__init__.py
archielle_tools/config.py
archielle_tools/db_utils.py
archielle_tools/klaviyo.py
archielle_tools/perfexcrm.py
archielle_tools/utils.py
archielle_tools-0.0.2.dist-info/LICENSE
archielle_tools-0.0.2.dist-info/METADATA
archielle_tools-0.0.2.dist-info/WHEEL
archielle_tools-0.0.2.dist-info/top_level.txt
archielle_tools-0.0.2.dist-info/RECORD
