Metadata-Version: 2.1
Name: archielle-tools
Version: 0.0.2
Summary: Archielle tools library.
Author: Collin Paran
Author-email: collin@collinparan.com
Classifier: Programming Language :: Python :: 3
Classifier: License :: OSI Approved :: MIT License
Classifier: Operating System :: OS Independent
Requires-Python: >=3.6
License-File: LICENSE
Requires-Dist: requests
Requires-Dist: pandas
Requires-Dist: mysql-connector-python
